{
  "schema_version": "nara-pre-dashboard-v4",
  "generated_at": "2026-07-04 02:01:31 KST",
  "dashboard_updated": true,
  "source_files": {
    "raw": "/Users/dori/.hermes/profiles/jobdori/work/nara_raw_v4_mac_latest.json",
    "filtered": "/Users/dori/.hermes/profiles/jobdori/data/nara_jangteo/output/nara_filtered_v4_mac_latest.json",
    "attachment_summaries": "/Users/dori/nara-dashboard/nara_attachment_summaries_v4.json",
    "mode": "mac_fallback_no_mj_linux"
  },
  "summary": {
    "total_judged_bids": 129,
    "active_candidates": 2,
    "attachment_queue": 2,
    "order_plans": 14,
    "likely_eligible": 2,
    "conditional": 0,
    "review_budget": 680090909,
    "attachment_processed": 2,
    "attachment_with_downloads": 0,
    "attachment_errors": 0,
    "documents_extracted": 0,
    "documents_extract_ok": 0,
    "documents_needs_review": 2,
    "ready_for_dashboard": 2
  },
  "attachment_errors": [],
  "ready_items": [
    {
      "uid": "R26BK01607482-000",
      "source": "입찰공고",
      "source_system": "data.go.kr:PubDataOpnStdService",
      "bid_no": "R26BK01607482",
      "order": "000",
      "name": "우강면 기초생활거점조성사업(2단계) 지역역량강화 용역",
      "category": "농촌/생활거점",
      "matched_terms": [
        "기초생활거점",
        "역량강화"
      ],
      "excluded_terms": [],
      "status": "active",
      "agency": "당진도시공사",
      "demand_agency": "당진도시공사",
      "notice_date": "2026-06-30",
      "deadline": "2026-07-15T13:00:00+09:00",
      "deadline_text": "",
      "budget": "345090909",
      "method": "일반경쟁",
      "region_limit": "",
      "industry_limit": "학술.연구용역",
      "url": "https://www.g2b.go.kr/link/PNPE027_01/single/?bidPbancNo=R26BK01607482&bidPbancOrd=000",
      "needs_detail": true,
      "auto_judge": {
        "level": "A",
        "judgment": "적합",
        "explanation": "메타데이터 기준 명확히 조건 부합 — 첨부파일 없이 확정 가능",
        "score": 14,
        "reasons": [
          "도시재생 핵심: ['기초생활거점']",
          "용역 유형 적합: ['역량강화']",
          "농촌/생활거점 분류",
          "교수법인 적합 업종",
          "예산 적정 (345,090,909원)"
        ]
      },
      "detail_priority": 104,
      "ai_review_status": "not_needed"
    },
    {
      "uid": "R26BK01607511-000",
      "source": "입찰공고",
      "source_system": "data.go.kr:PubDataOpnStdService",
      "bid_no": "R26BK01607511",
      "order": "000",
      "name": "순성면 본2리·합덕읍 신석리 취약지역생활여건개조사업 휴먼케어 및 주민역량강화 용역",
      "category": "취약지역/주거",
      "matched_terms": [
        "생활여건",
        "역량강화",
        "주민역량",
        "취약지역"
      ],
      "excluded_terms": [],
      "status": "active",
      "agency": "당진도시공사",
      "demand_agency": "당진도시공사",
      "notice_date": "2026-06-30",
      "deadline": "2026-07-16T13:00:00+09:00",
      "deadline_text": "",
      "budget": "335000000",
      "method": "일반경쟁",
      "region_limit": "",
      "industry_limit": "학술.연구용역",
      "url": "https://www.g2b.go.kr/link/PNPE027_01/single/?bidPbancNo=R26BK01607511&bidPbancOrd=000",
      "needs_detail": true,
      "auto_judge": {
        "level": "A",
        "judgment": "적합",
        "explanation": "메타데이터 기준 명확히 조건 부합 — 첨부파일 없이 확정 가능",
        "score": 17,
        "reasons": [
          "도시재생 핵심: ['취약지역생활여건']",
          "도시재생 연관: ['주민역량']",
          "용역 유형 적합: ['역량강화']",
          "취약지역/주거 분류",
          "교수법인 적합 업종",
          "예산 적정 (335,000,000원)"
        ]
      },
      "detail_priority": 107,
      "ai_review_status": "not_needed"
    }
  ],
  "dashboard_updated_at": "2026-07-04T02:01:31+09:00",
  "eligibility_filter": {
    "mode": "mac_fallback_direct_public_items",
    "criteria": [
      "active only",
      "auto_judge == 적합",
      "region limit empty/경기도/수원/전국",
      "exclude design, architect-office, asbestos, construction-management style work"
    ],
    "original_ready_items": 33,
    "kept_ready_items": 2,
    "removed_ready_items": 31,
    "previous_dashboard_generated_at": "2026-07-03 02:01:53 KST"
  }
}